staple/__init__.py
staple/account.py
staple/groups.py
staple_ai-0.0.1.dist-info/LICENSE
staple_ai-0.0.1.dist-info/METADATA
staple_ai-0.0.1.dist-info/WHEEL
staple_ai-0.0.1.dist-info/top_level.txt
staple_ai-0.0.1.dist-info/RECORD
